amkiller/__init__.py
amkiller/killer.py
amkiller-0.0.1.dist-info/METADATA
amkiller-0.0.1.dist-info/WHEEL
amkiller-0.0.1.dist-info/licenses/LICENSE
amkiller-0.0.1.dist-info/RECORD
